PaperProcessor/halt.v
//////////////////////////////////////////////////////////////////////////////////
// Module Name: halt.v
// Description: takes clock input and according to the current instruction it 
// determines if the clock should go on or not
//////////////////////////////////////////////////////////////////////////////////

`timescale 1ns / 1ns

module halt(pulses, clk, instruct);

//−−−−−−−−−−−−−Input Ports−−−−−−−−−−−−−−−−−−−−−−−−−−−−−

input [1:0] instruct; 	//input a 2 bit register from JNO
input clk;

//−−−−−−−−−−−−−Output Ports−−−−−−−−−−−−−−−−−−−−−−−−−−−−

output pulses;

//−−−−−−−−−−−−−Input ports Data Type−−−−−−−−−−−−−−−−−−−
// By rule all the input ports should be wires
wire [1:0] instruct;
wire clk;

//−−−−−−−−−−−−−Output Ports Data Type−−−−−−−−−−−−−−−−−−
// Output port can be a storage element (reg) or a wire
wire pulses;

//−−−−−−−−−−−−−Intermediate Wires----−−−−−−−−−−−−−−−−−−
wire w1;
wire w2;

//−−−−−−----−-−−−−−−Instructions---−−−−−−−−−−−−−−−--−−−

and a1(w1, instruct[1], !instruct[0]);
not n1(w2, w1);

and(pulses, clk, w2);

endmodule

PaperProcessor/dff.v
//////////////////////////////////////////////////////////////////////////////////
// Module Name: dff.v
// Description: D flip flop that sets and resets at negedge
//////////////////////////////////////////////////////////////////////////////////

`timescale 1ns / 1ns

module dff (clk, s, r, d, q, qbar);
	input clk, s, r, d;
	output q,qbar;
	reg q,qbar;
	always @(negedge r) begin
		q = 1'b0;
		qbar = 1'b1;
		end
	always @(negedge s) begin
		q = 1'b1;
		qbar = 1'b0;
		end
	always @(posedge clk) begin
		#1
		q = d;
		qbar = ~d;
		end

endmodule

PaperProcessor/jno.v
//////////////////////////////////////////////////////////////////////////////////
// Module Name: jno.v
// Description: from the current instructions, outputs ENABLE for checking and counter 
//////////////////////////////////////////////////////////////////////////////////
`timescale 1ns/1ns

module jno(enabling, enabling_sta, openpulse, sta, instruct, pulses);

//−−−−−−−−−−−−−Input Ports−−−−−−−−−−−−−−−−−−−−−−−−−−−−−

input [1:0] instruct; 	//input a 2 bit register from JNO
input pulses;
input sta;

//−−−−−−−−−−−−−Output Ports−−−−−−−−−−−−−−−−−−−−−−−−−−−−

output enabling;
output enabling_sta;
output openpulse;

//−−−−−−−−−−−−−Input ports Data Type−−−−−−−−−−−−−−−−−−−
// By rule all the input ports should be wires
wire [1:0] instruct;
wire pulses;
wire sta;

//−−−−−−−−−−−−−Output Ports Data Type−−−−−−−−−−−−−−−−−−
// Output port can be a storage element (reg) or a wire
wire enabling;
wire enabling_sta;

//−−−−−−−−−−−−−Intermediate Wires----−−−−−−−−−−−−−−−−−−
reg s;
reg r;
wire notenabling, notenabling_sta;
wire w1, w2;
reg mem;
reg pulser;
wire openpulse;
reg openpulser;

//−−−−−−----−-−−−−−−Instructions---−−−−−−−−−−−−−−−--−−−
initial begin
s = 0;
r = 0;
pulser = 0;
openpulser = 0;
end

and a1(w1, !instruct[1], instruct[0]);
and a2(w2, !sta, !instruct[1], instruct[0]);
and a3 (openpulse, !sta, openpulser);

always @(posedge w1)
begin
	#1
	pulser = 1;
	#8
	openpulser = 1;
	#4
	openpulser = 0;
	#1
	pulser = 0;
	#1
	pulser = 1;
	#1
	pulser = 0;
end
dff dff3(pulser, s, r, w1, enabling, notenabling); //enabling the checking
dff dff4(pulser, s, r, w2, enabling_sta, notenabling_sta); //enabling for counter

endmodule

PaperProcessor/two_bit_fa.v
//////////////////////////////////////////////////////////////////////////////////
// Module Name: fulladder.v
// Description: Full Adder where 1 is always added to the previous number
//////////////////////////////////////////////////////////////////////////////////

`timescale 1ns / 1ns

module fulladder(stat, sum, a);

//−−−−−−−−−−−−−Input Ports−−−−−−−−−−−−−−−−−−−−−−−−−−−−−

inout [1:0] a; //input a 2 bit register

//−−−−−−−−−−−−−Output Ports−−−−−−−−−−−−−−−−−−−−−−−−−−−−

output [1:0] sum; //output 2 bit registers
output stat; //see whether registers overflown

//−−−−−−−−−−−−−Input ports Data Type−−−−−−−−−−−−−−−−−−−
// By rule all the input ports should be wires
wire [1:0] a;
wire [1:0] b;

//−−−−−−−−−−−−−Output Ports Data Type−−−−−−−−−−−−−−−−−−
// Output port can be a storage element (reg) or a wire
wire [1:0] sum;
wire stat;

//−−−−−−−−−−−−−Intermediate Wires----−−−−−−−−−−−−−−−−−−
wire w0, w1, w2, w3, w_sum0, w_sum1, w_stat;

//−−−−−−----−-−−−−−−Instructions---−−−−−−−−−−−−−−−--−−−
//set LSB of input to w_sum0
xor u0(w_sum0,a[0], 1'b1);
and (sum[0], w_sum0, 1);

//set MSB of input to w_sum1
and u1(w0, a[0], 1'b1);
xor u2(w1, a[1], 1'b0);
and u3(w2, a[1], 1'b0);
and u4(w3, w0, w1);
xor u5(w_sum1, w0, w1);
and(sum[1], w_sum1,1);

//set carry out to be w_stat
or  u6(w_stat,w2, w3);
and (stat, w_stat,1);

endmodule

PaperProcessor/increment.v
//////////////////////////////////////////////////////////////////////////////////
// Module Name: increment.v
// Description: increments 2-bit value from previous
//////////////////////////////////////////////////////////////////////////////////

`timescale 1ns / 1ns

`include "two_bit_fa.v"

module increment(value, sta, pulser, mn, prev_value, instruct);

//−−−−−−−−−−−−−Input Ports−−−−−−−−−−−−−−−−−−−−−−−−−−−−−

input [1:0] instruct; 	//input a 2 bit register from JNO
input [1:0] prev_value;
input pulser;

//−−−−−−−−−−−−−Output Ports−−−−−−−−−−−−−−−−−−−−−−−−−−−−

inout [1:0] value;
output sta;
output mn;

//−−−−−−−−−−−−−Input ports Data Type−−−−−−−−−−−−−−−−−−−
// By rule all the input ports should be wires
wire [1:0] instruct;
wire [1:0] clk;
wire [1:0] prev_value;
wire pulse;

//−−−−−−−−−−−−−Output Ports Data Type−−−−−−−−−−−−−−−−−−
// Output port can be a storage element (reg) or a wire
wire [1:0] value;
wire sta;
reg mn;
wire w1;

//−−−−−−−−−−−−−Intermediate Wires----−−−−−−−−−−−−−−−−−−


//−−−−−−----−-−−−−−−Instructions---−−−−−−−−−−−−−−−--−−−

and (w1, pulser, !instruct[1], !instruct[0]);
initial begin
mn = 0;
end

always @(posedge w1)
begin
	#1
	mn = 1;
	#2
	mn = 0;
end

fulladder adder(sta, value, prev_value);

endmodule

PaperProcessor/checking.v
//////////////////////////////////////////////////////////////////////////////////
// Module Name: checking.v
// Description: checks if either of two inputs is HIGH at a certain time
//////////////////////////////////////////////////////////////////////////////////

`timescale 1ns / 1ns

module checking(checked, enabling, check);

//−−−−−−−−−−−−−Input Ports−−−−−−−−−−−−−−−−−−−−−−−−−−−−−

input [1:0] check; 	//input a 2 bit register from JNO
input enabling;

//−−−−−−−−−−−−−Output Ports−−−−−−−−−−−−−−−−−−−−−−−−−−−−

output [1:0] checked;

//−−−−−−−−−−−−−Input ports Data Type−−−−−−−−−−−−−−−−−−−
// By rule all the input ports should be wires
wire [1:0] check;
wire enabling;

//−−−−−−−−−−−−−Output Ports Data Type−−−−−−−−−−−−−−−−−−
// Output port can be a storage element (reg) or a wire
wire [1:0] checked;

//−−−−−−−−−−−−−Intermediate Wires----−−−−−−−−−−−−−−−−−−


//−−−−−−----−-−−−−−−Instructions---−−−−−−−−−−−−−−−--−−−

or o1(checked[1], enabling, check[1]);
or o2(checked[0], enabling, check[0]);


endmodule

PaperProcessor/dfff.v
//////////////////////////////////////////////////////////////////////////////////
// Module Name: dfff.v
// Description: D flip flop that sets and resets at posedge
//////////////////////////////////////////////////////////////////////////////////

`timescale 1ns / 1ns

module dfff (clk, s, r, d, q, qbar);
	input clk, s, r, d;
	output q,qbar;
	reg q,qbar;
	always @(posedge r) begin
		q = 1'b0;
		qbar = 1'b1;
		end
	always @(posedge s) begin
		q = 1'b1;
		qbar = 1'b0;
		end
	always @(posedge clk) begin
		#1
		q = d;
		qbar = ~d;
		end

endmodule

PaperProcessor/programcounter.v
//////////////////////////////////////////////////////////////////////////////////
// Module Name: programcounter.v
// Description: counter
//////////////////////////////////////////////////////////////////////////////////

`timescale 1ns / 1ns

module programcounter(select, openpulse, R, jno, clk, enabled);

//−−−−−−−−−−−−−Input Ports−−−−−−−−−−−−−−−−−−−−−−−−−−−−−

input [1:0] jno; 	//input a 2 bit register from JNO
input clk;			//input clock signal
input enabled;		//input enabling JNO register addresses
input [1:0] R;		//for resetting
input openpulse;

//−−−−−−−−−−−−−Output Ports−−−−−−−−−−−−−−−−−−−−−−−−−−−−

output [1:0] select;

//−−−−−−−−−−−−−Input ports Data Type−−−−−−−−−−−−−−−−−−−
// By rule all the input ports should be wires
wire [1:0] jno;
wire clk;
wire enabled;
wire [1:0] R;
wire openpulse;

//−−−−−−−−−−−−−Output Ports Data Type−−−−−−−−−−−−−−−−−−
// Output port can be a storage element (reg) or a wire
wire [1:0] select;

//−−−−−−−−−−−−−Intermediate Wires----−−−−−−−−−−−−−−−−−−

wire [1:0] selectN;
wire w1, w2,w3,w4, w5, w6;
wire [1:0] D;
wire [1:0] S;
wire [1:0] R_temp;

//−−−−−−----−-−−−−−−Instructions---−−−−−−−−−−−−−−−--−−−
and a1(S[0], openpulse, enabled, jno[0]);
and a2(S[1], openpulse, enabled, jno[1]);
and a3(w3, openpulse, enabled, !jno[0]); 
and a4(w4, openpulse, enabled, !jno[1]);
or o1(R_temp[0], w3, R[0]); //R[0] is 0, w1 goes from 0 to 1
or o2(R_temp[1], w4, R[1]); //


dfff dff0(clk, S[0], R_temp[0], D[0], select[0], selectN[0]);
dfff dff1(clk, S[1], R_temp[1], D[1], select[1], selectN[1]);

and (w1, selectN[0], select[1]);
and (w2, selectN[1], select[0]);
or (D[1], w1, w2);
and (D[0], selectN[0],1);

endmodule

PaperProcessor/twoBitRam.v
//////////////////////////////////////////////////////////////////////////////////
// Module Name: twoBitRam.v
// Description: determines data outputs from address
//////////////////////////////////////////////////////////////////////////////////

`timescale 1ns / 1ns

module twoBitRam(addr, data);

parameter Instructions = "./instruct.bin";

//−−−−−−−−−−−−−Input Ports−−−−−−−−−−−−−−−−−−−−−−−−−−−−−

input [1:0] addr;

//−−−−−−−−−−−−−Output Ports−−−−−−−−−−−−−−−−−−−−−−−−−−−−

output [1:0] data;

//−−−−−−−−−−−−−Input ports Data Type−−−−−−−−−−−−−−−−−−−
// By rule all the input ports should be wires
wire [1:0] addr; 

//−−−−−−−−−−−−−Output Ports Data Type−−−−−−−−−−−−−−−−−−
// Output port can be a storage element (reg) or a wire
wire [1:0] data;


//−−−−−−----−-−−−−−−Instructions---−−−−−−−−−−−−−−−--−−−
/*
Instructions:
INC: 00
JNO: 01
HLT: 10

in1: INC
in2: JNO
in3: 00
in4: HLT
*/

//-------------Save Instructions In Ram----------------
reg [1:0] ram_reg [0:3];                // make register 2 bits wide  and 4 bits long
        initial begin
                $readmemb(Instructions, ram_reg);       // load program
        end
assign data = ram_reg[addr];

/*
//First Demux
//and and1_msb(a1_msb, !addr[1], !addr[0], 1'b0);
//and and2_msb(a2_msb, !addr[1], addr[0], 1'b0);
//and and3_msb(a3_msb, addr[1], !addr[0], 1'b0);
//and and4_msb(a4_msb, addr[1], addr[0], 1'b1);

//Second Demux
and and1_lsb(a1_lsb, !addr[1], !addr[0], 1'b0);
and and2_lsb(a2_lsb, !addr[1], addr[0], 1'b1);
and and3_lsb(a3_lsb, addr[1], !addr[0], 1'b0);
and and4_lsb(a4_lsb, addr[1], addr[0], 1'b0);

//Final Or Gate
or or_msb(data[1],a1_msb,a2_msb,a3_msb,a4_msb);
or or_lsb(data[0],a1_lsb,a2_lsb,a3_lsb,a4_lsb);
*/

endmodule

PaperProcessor_new/testbench.v

//////////////////////////////////////////////////////////////////////////////////
// Module Name: 2-bit fulladder 
// Description: This is last updated 2/19/2016 3:11 am. When ran this should 
// print out only the increment logic
// Author: Andy Jeong
// Note: in this adder, one is always adding 1 to the previous number
//////////////////////////////////////////////////////////////////////////////////

`include "twoBitRam.v"
`include "increment.v"
`include "programcounter.v"
`include "halt.v"
`include "jno.v"
`include "checking.v"
`include "dff.v"
`include "dfff.v"

module test_tb(); 

reg status; 						// status register
reg clock; 							// clock register
wire monostable;					// monostable clock induced by inc logic
wire pulse;							// clock induced by halt
wire monostabler;
reg [1:0] out; 						// output registers
wire w3, w4, w5, w6;
wire openpulser;					//Pulse from JNO, imitating monostable timer

reg [1:0] constant; 				// INC logic: add to full adder
wire [1:0] adder_to_out; 			// INC logic :connect adder to reg out
wire adder_to_stat;					// ING logic: ddding to status
wire [1:0] instruct; 				// output instruction from RAM (LSB)
wire [1:0] instructA;				// actual instruction after checking
reg [1:0] Resetter;					//used to initialize the program counter

wire enabled, enabled_sta;
wire [1:0] PC;						// Counter: program counter output

initial begin

	//print out things to monitor
	$monitor ("time = %g\t PC = %b instruct = %b out = %b stat = %b", $time, PC, instruct, out, status);

	clock = 0; 				// initialize clock to be 0
	status = 0; 			// initialize status to be 0

	out= 2'b00; 			// initialize value register
	Resetter= 2'b00;		// Resettting logic

	#1 Resetter = 2'b11;	//Resetting program counter
	#1 Resetter= 2'b00;

 	//let the simulation run for 80 seconds
	#80 $finish;
end

always @(posedge monostabler)
begin
	out[0] <= adder_to_out[0];
	out[1] <= adder_to_out[1];
	status <= adder_to_stat;
end

always begin
	#4 clock = ~clock; // Generate clock
end

twoBitRam ram1(PC,instruct); 												//twoBitRam
programcounter pc(PC, openpulser, Resetter, instruct, pulse, enabled_sta); 	//Program Counter
and a1(monostabler, monostable, !status);									//monostable for adder
checking checkers(instructA, enabled, instruct);							//Check JNO

//instructional logic
increment inc(adder_to_out, adder_to_stat,pulse, monostable, out,instructA);//INC
jno jnoo(enabled, enabled_sta, openpulser, status, instructA, pulse);		//JNO
halt hlt(pulse, clock, instructA);											//HLT


endmodule

PaperProcessor/pp.vcd
$date
	Mon Feb 22 16:16:23 2016
$end
$version
	Icarus Verilog
$end
$timescale
	1ns
$end
$scope module test_tb $end
$var wire 1 ! monostabler $end
$var wire 1 " pulse $end
$var wire 1 # openpulser $end
$var wire 1 $ monostable $end
$var wire 2 % instructA [1:0] $end
$var wire 2 & instruct [1:0] $end
$var wire 1 ' enabled_sta $end
$var wire 1 ( enabled $end
$var wire 1 ) adder_to_stat $end
$var wire 2 * adder_to_out [1:0] $end
$var wire 2 + PC [1:0] $end
$var reg 2 , Resetter [1:0] $end
$var reg 1 - clock $end
$var reg 2 . constant [1:0] $end
$var reg 2 / out [1:0] $end
$var reg 1 0 status $end
$scope module checkers $end
$var wire 1 ( enabling $end
$var wire 2 1 checked [1:0] $end
$var wire 2 2 check [1:0] $end
$upscope $end
$scope module hlt $end
$var wire 1 - clk $end
$var wire 2 3 instruct [1:0] $end
$var wire 1 " pulses $end
$var wire 1 4 w1 $end
$var wire 1 5 w2 $end
$upscope $end
$scope module inc $end
$var wire 2 6 instruct [1:0] $end
$var wire 2 7 prev_value [1:0] $end
$var wire 1 " pulser $end
$var wire 1 8 w1 $end
$var wire 2 9 value [1:0] $end
$var wire 1 ) sta $end
$var reg 1 $ mn $end
$scope module adder $end
$var wire 2 : a [1:0] $end
$var wire 1 ) stat $end
$var wire 1 ; w0 $end
$var wire 1 < w1 $end
$var wire 1 = w2 $end
$var wire 1 > w3 $end
$var wire 1 ? w_stat $end
$var wire 1 @ w_sum0 $end
$var wire 1 A w_sum1 $end
$var wire 2 B sum [1:0] $end
$upscope $end
$upscope $end
$scope module jnoo $end
$var wire 2 C instruct [1:0] $end
$var wire 1 # openpulse $end
$var wire 1 " pulses $end
$var wire 1 0 sta $end
$var wire 1 D w1 $end
$var wire 1 E w2 $end
$var wire 1 F notenabling_sta $end
$var wire 1 G notenabling $end
$var wire 1 ' enabling_sta $end
$var wire 1 ( enabling $end
$var reg 1 H openpulser $end
$var reg 1 I pulser $end
$var reg 1 J r $end
$var reg 1 K s $end
$scope module dff3 $end
$var wire 1 I clk $end
$var wire 1 D d $end
$var wire 1 J r $end
$var wire 1 K s $end
$var reg 1 ( q $end
$var reg 1 G qbar $end
$upscope $end
$scope module dff4 $end
$var wire 1 I clk $end
$var wire 1 E d $end
$var wire 1 J r $end
$var wire 1 K s $end
$var reg 1 ' q $end
$var reg 1 F qbar $end
$upscope $end
$upscope $end
$scope module pc $end
$var wire 2 L R [1:0] $end
$var wire 1 " clk $end
$var wire 1 ' enabled $end
$var wire 1 # openpulse $end
$var wire 1 M w1 $end
$var wire 1 N w2 $end
$var wire 1 O w3 $end
$var wire 1 P w4 $end
$var wire 2 Q selectN [1:0] $end
$var wire 2 R select [1:0] $end
$var wire 2 S jno [1:0] $end
$var wire 2 T S [1:0] $end
$var wire 2 U R_temp [1:0] $end
$var wire 2 V D [1:0] $end
$scope module dff0 $end
$var wire 1 " clk $end
$var wire 1 W d $end
$var wire 1 X r $end
$var wire 1 Y s $end
$var reg 1 Z q $end
$var reg 1 [ qbar $end
$upscope $end
$scope module dff1 $end
$var wire 1 " clk $end
$var wire 1 \ d $end
$var wire 1 ] r $end
$var wire 1 ^ s $end
$var reg 1 _ q $end
$var reg 1 ` qbar $end
$upscope $end
$upscope $end
$scope module ram1 $end
$var wire 2 a addr [1:0] $end
$var wire 2 b data [1:0] $end
$upscope $end
$upscope $end
$enddefinitions $end
#0
$dumpvars
bx b
bx a
x`
x_
0^
0]
x\
x[
xZ
0Y
0X
xW
bx V
b0 U
b0 T
bx S
bx R
bx Q
0P
0O
xN
xM
b0 L
0K
0J
0I
0H
1G
1F
xE
xD
bx C
b1 B
0A
1@
0?
0>
0=
0<
0;
b0 :
b1 9
08
b0 7
bx 6
x5
x4
bx 3
bx 2
bx 1
00
b0 /
b1 .
0-
b0 ,
bx +
b1 *
0)
0(
0'
bx &
bx %
0$
0#
0"
0!
$end
#1
15
04
0D
0E
0\
1W
b1 V
b0 %
b0 1
b0 3
b0 6
b0 C
0N
0M
1[
b0 &
b0 2
b0 S
b0 b
0Z
b11 Q
1`
b0 +
b0 R
b0 a
0_
1X
1]
b11 U
b11 ,
b11 L
#2
0X
0]
b0 U
b0 ,
b0 L
#4
18
1"
1-
#5
b10 *
b10 9
b10 B
1A
0@
1;
b1 /
b1 7
b1 :
1\
08
1D
1E
0W
b10 V
1N
b1 %
b1 1
b1 3
b1 6
b1 C
1!
1$
b10 Q
0[
b1 &
b1 2
b1 S
b1 b
b1 +
b1 R
b1 a
1Z
#6
1I
#7
0D
0E
b11 %
b11 1
b11 3
b11 6
b11 C
0!
0G
1(
0F
1'
0$
#8
0"
0-
#12
1"
1-
#13
1W
1M
b11 V
0N
0`
1_
b1 Q
1[
b0 &
b0 2
b0 S
b0 b
b10 +
b10 R
b10 a
0Z
#14
0\
b1 V
0M
b11 Q
1`
b0 +
b0 R
b0 a
0_
1X
1]
b11 U
1O
1P
1#
1H
#16
0"
0-
#18
0X
0]
b0 U
0O
0P
0#
0H
#19
0I
#20
1"
1I
1-
#21
1\
1D
1E
0W
08
b10 V
1N
b1 %
b1 1
b1 3
b1 6
b1 C
b10 Q
0[
b1 &
b1 2
b1 S
b1 b
b1 +
b1 R
b1 a
1Z
1F
0'
1G
0(
0I
#22
b11 *
b11 9
b11 B
1<
1@
0;
b10 /
b10 7
b10 :
1!
1I
1$
#23
0D
0E
b11 %
b11 1
b11 3
b11 6
b11 C
0G
1(
0F
1'
#24
0!
0"
0$
0-
#28
1"
1-
#29
1W
1M
b11 V
0N
0`
1_
b1 Q
1[
b0 &
b0 2
b0 S
b0 b
b10 +
b10 R
b10 a
0Z
#30
0\
b1 V
0M
b11 Q
1`
b0 +
b0 R
b0 a
0_
1X
1]
b11 U
1O
1P
1#
1H
#32
0"
0-
#34
0X
0]
b0 U
0O
0P
0#
0H
#35
0I
#36
1"
1I
1-
#37
1\
1D
1E
0W
08
b10 V
1N
b1 %
b1 1
b1 3
b1 6
b1 C
b10 Q
0[
b1 &
b1 2
b1 S
b1 b
b1 +
b1 R
b1 a
1Z
1F
0'
1G
0(
0I
#38
1)
1?
b0 *
b0 9
b0 B
1>
0A
0@
1;
b11 /
b11 7
b11 :
1!
1I
1$
#39
0D
0E
b11 %
b11 1
b11 3
b11 6
b11 C
0G
1(
0F
1'
#40
0!
0"
0$
0-
#44
1"
1-
#45
1W
1M
b11 V
0N
0`
1_
b1 Q
1[
b0 &
b0 2
b0 S
b0 b
b10 +
b10 R
b10 a
0Z
#46
0\
b1 V
0M
b11 Q
1`
b0 +
b0 R
b0 a
0_
1X
1]
b11 U
1O
1P
1#
1H
#48
0"
0-
#50
0X
0]
b0 U
0O
0P
0#
0H
#51
0I
#52
1"
1I
1-
#53
1\
1D
1E
0W
08
b10 V
1N
b1 %
b1 1
b1 3
b1 6
b1 C
b10 Q
0[
b1 &
b1 2
b1 S
b1 b
b1 +
b1 R
b1 a
1Z
1F
0'
1G
0(
0I
#54
0)
0?
b1 *
b1 9
b1 B
0>
0<
1@
0;
0E
10
b0 /
b0 7
b0 :
0!
1I
1$
#55
0D
b11 %
b11 1
b11 3
b11 6
b11 C
0G
1(
#56
0"
0$
0-
#60
1"
1-
#61
1W
1M
b11 V
0N
0`
1_
b1 Q
1[
b0 &
b0 2
b0 S
b0 b
b10 +
b10 R
b10 a
0Z
#62
1H
#64
0"
0-
#66
0H
#67
0I
#68
1"
1I
1-
#69
0"
05
0\
14
0W
08
0M
b0 V
b10 %
b10 1
b10 3
b10 6
b10 C
b0 Q
0[
b10 &
b10 2
b10 S
b10 b
b11 +
b11 R
b11 a
1Z
1G
0(
0I
#70
1$
#72
0$
0-
