paper-processor/ram.v
//-------ram module
module ram(address, out);

parameter Instructions = "./instruct.bin";
input [1:0] address;

output [1:0] out;

// By rule all the input ports should be wires
wire [1:0] address;

// Output port can be a storage element (reg) or a wire
wire [1:0] out;

//-------------Save Instructions In Ram----------------
reg [1:0] ram_reg [0:3];                // make register 2 bits wide  and 4 bits long
        initial begin
                $readmemb(Instructions, ram_reg);       // load program
        end
assign out = ram_reg[address];

endmodule

paper-processor/setAddress.v
//-------setAddress module
module setAddress(address, status, counter); 

input [1:0] counter;
input status;
output [1:0] address;

wire [1:0] w; 

//determining address bits            
and a1(w[0], counter[1], ~counter[0]);
or data1(address[1], w[0], status);

and a2(w[1], ~counter[1], counter[0]);
or data2(address[0], w[1], status);

endmodule

paper-processor/register.v
//-------register module
module register(clk, status, count, register);
  parameter n = 1;
 
  output reg [n:0] register;
  input [n:0] count;
  input status, clk;
 
  // Set the initial value
  initial 
      register <= 2'b00;

  always @(posedge clk) begin     //incrementing register values
    if ((status == 0) && (count == 01)) 
          register = register + 01;
    if(register == 11) 
          register = register + 01;

    end
  always @(posedge status)                //when overflow, set register to 00
          register = 00;

endmodule

paper-processor/counter.v
//-------counter module
module counter(count, clk, rst);
  parameter n = 1;
 
  output reg [n:0] count;
  input clk;
  input rst;
 
  // Set the initial value
  initial
    count = 0;
 
  // Increment count on clock
  always @(posedge clk or negedge rst)
    if (!rst)
      count = 0;
    else begin
      count = count + 1;
      if(count == 2'b11)
          count = 2'b00;
    end
endmodule

paper-processor/paperprocessor.v
/*
// School: The Cooper Union
// Course: ECE151A Spring 2016
// Assignment: Paper Processor
// Group members: Andy Jeong, Brenda So, Gordon Macshane
// Date: 2/22/2016
//
//−−−−−−----−-−−−−−−Instructions---−−−−−−−−−−−−−−−--−−−
//	Instructions:
//		INC: 00(2)
//		JNO: 01(2)
//		HLT: 10(2)
//
//	Instructions for the 2-bit paper processor:
//			IS1: 	INC
//			IS2,3:  JNO 00(2)
//			IS4: 	HLT
*/
`include "counter.v"
`include "ram.v"
`include "setAddress.v"
`include "register.v"
`timescale 1ns/1ns

//-------testbench for paper-processor
// See below for the implemented modules

module paperprocessor();

reg clk;                         //clock
reg status;                      //status
wire [1:0] a;                    //address
wire [1:0] data;                 //data
wire [1:0] count;                //counter
wire [1:0] register;             //register values
reg reset;                       //reset


initial fork                     //initialization run in parallel 
	  clk = 0;	
		reset = 1;
		status = 0;
		$monitor ( "clk =%g s = %b addr=%b%b reg = %b data = %b%b", 
              clk, status,  a[1], a[0], register, data[1], data[0]);
		#20 status = ~status;
		#22 $finish;   
join

initial begin
	   $dumpfile ("paper.vcd");    //waveform file in .vcd format
     $dumpvars;
end

always begin                     //clock toggle
	#1 clk = ~clk;
end

counter counter0(count, clk, reset);
register register0(clk, status, count, register);
setAddress setaddress0(a, status, count); 
ram ram0(a, data);

endmodule

paper-processor/paper.vcd
$date
	Mon Feb 22 01:36:38 2016
$end
$version
	Icarus Verilog
$end
$timescale
	1ns
$end
$scope module paperprocessor $end
$var wire 2 ! register [1:0] $end
$var wire 2 " data [1:0] $end
$var wire 2 # count [1:0] $end
$var wire 2 $ a [1:0] $end
$var reg 1 % clk $end
$var reg 1 & reset $end
$var reg 1 ' status $end
$scope module counter0 $end
$var wire 1 % clk $end
$var wire 1 & rst $end
$var reg 2 ( count [1:0] $end
$upscope $end
$scope module ram0 $end
$var wire 2 ) out [1:0] $end
$var wire 2 * address [1:0] $end
$upscope $end
$scope module register0 $end
$var wire 1 % clk $end
$var wire 2 + count [1:0] $end
$var wire 1 ' status $end
$var reg 2 , register [1:0] $end
$upscope $end
$scope module setaddress0 $end
$var wire 2 - counter [1:0] $end
$var wire 1 ' status $end
$var wire 2 . w [1:0] $end
$var wire 2 / address [1:0] $end
$upscope $end
$upscope $end
$enddefinitions $end
#0
$dumpvars
b0 /
b0 .
b0 -
b0 ,
b0 +
b0 *
b0 )
b0 (
0'
1&
0%
b0 $
b0 #
b0 "
b0 !
$end
#1
b1 "
b1 )
b1 $
b1 *
b1 /
b10 .
b1 #
b1 (
b1 +
b1 -
1%
#2
0%
#3
b0 "
b0 )
b10 $
b10 *
b10 /
b1 .
b10 #
b10 (
b10 +
b10 -
b1 !
b1 ,
1%
#4
0%
#5
b0 $
b0 *
b0 /
b0 .
b0 #
b0 (
b0 +
b0 -
1%
#6
0%
#7
b1 "
b1 )
b1 $
b1 *
b1 /
b10 .
b1 #
b1 (
b1 +
b1 -
1%
#8
0%
#9
b0 "
b0 )
b10 $
b10 *
b10 /
b1 .
b10 #
b10 (
b10 +
b10 -
b10 !
b10 ,
1%
#10
0%
#11
b0 $
b0 *
b0 /
b0 .
b0 #
b0 (
b0 +
b0 -
1%
#12
0%
#13
b1 "
b1 )
b1 $
b1 *
b1 /
b10 .
b1 #
b1 (
b1 +
b1 -
1%
#14
0%
#15
b0 "
b0 )
b10 $
b10 *
b10 /
b1 .
b10 #
b10 (
b10 +
b10 -
b11 !
b11 ,
1%
#16
0%
#17
b0 $
b0 *
b0 /
b0 .
b0 #
b0 (
b0 +
b0 -
1%
#18
0%
#19
b1 "
b1 )
b1 $
b1 *
b1 /
b10 .
b1 #
b1 (
b1 +
b1 -
1%
#20
b0 !
b0 ,
b10 "
b10 )
b11 $
b11 *
b11 /
0%
1'
#21
b1 .
b10 #
b10 (
b10 +
b10 -
1%
